honeybee_grasshopper_core/__init__.py
honeybee_grasshopper_core/src/HB Add Prefix.py
honeybee_grasshopper_core/src/HB Add Shade.py
honeybee_grasshopper_core/src/HB Add Subface.py
honeybee_grasshopper_core/src/HB Aperture.py
honeybee_grasshopper_core/src/HB Apertures by Guide Surface.py
honeybee_grasshopper_core/src/HB Apertures by Ratio.py
honeybee_grasshopper_core/src/HB Apertures by Width Height.py
honeybee_grasshopper_core/src/HB Automatic Zoning.py
honeybee_grasshopper_core/src/HB Check Versions.py
honeybee_grasshopper_core/src/HB Color Face Attributes.py
honeybee_grasshopper_core/src/HB Color Room Attributes.py
honeybee_grasshopper_core/src/HB Config.py
honeybee_grasshopper_core/src/HB Custom Ground.py
honeybee_grasshopper_core/src/HB Deconstruct Model.py
honeybee_grasshopper_core/src/HB Deconstruct Object.py
honeybee_grasshopper_core/src/HB Door.py
honeybee_grasshopper_core/src/HB Dump Compressed Objects.py
honeybee_grasshopper_core/src/HB Dump Objects.py
honeybee_grasshopper_core/src/HB Dump gbXML.py
honeybee_grasshopper_core/src/HB Envelope Edges.py
honeybee_grasshopper_core/src/HB Extruded Border Shades.py
honeybee_grasshopper_core/src/HB Facade Parameters.py
honeybee_grasshopper_core/src/HB Face.py
honeybee_grasshopper_core/src/HB Faces by Attribute.py
honeybee_grasshopper_core/src/HB Faces by BC.py
honeybee_grasshopper_core/src/HB Faces by Type.py
honeybee_grasshopper_core/src/HB Geometry Properties.py
honeybee_grasshopper_core/src/HB Intersect Solids.py
honeybee_grasshopper_core/src/HB Label Faces.py
honeybee_grasshopper_core/src/HB Label Rooms.py
honeybee_grasshopper_core/src/HB Load Compressed Objects.py
honeybee_grasshopper_core/src/HB Load Objects.py
honeybee_grasshopper_core/src/HB Load gbXML OSM IDF.py
honeybee_grasshopper_core/src/HB Louver Shades.py
honeybee_grasshopper_core/src/HB Mirror.py
honeybee_grasshopper_core/src/HB Model.py
honeybee_grasshopper_core/src/HB Move.py
honeybee_grasshopper_core/src/HB Object to String.py
honeybee_grasshopper_core-1.43.3.dist-info/licenses/LICENSE
honeybee_grasshopper_core-1.43.3.dist-info/METADATA
honeybee_grasshopper_core-1.43.3.dist-info/WHEEL
honeybee_grasshopper_core-1.43.3.dist-info/top_level.txt
honeybee_grasshopper_core-1.43.3.dist-info/RECORD
